{"an5.110:0.1":"Anguttara Nikaya 5.110 ","an5.110:0.2":"11. Phasuviharavagga ","an5.110:0.3":"Arannasutta ","an5.110:1.1":"“Pancahi, bhikkhave, dhammehi samannagato bhikkhu alam arannavanapatthani pantani senasanani patisevitum. ","an5.110:1.2":"Katamehi pancahi? ","an5.110:1.3":"Idha, bhikkhave, bhikkhu silava hoti …pe… samadaya sikkhati sikkhapadesu; ","an5.110:1.4":"bahussuto hoti …pe… ditthiya suppatividdha; ","an5.110:1.5":"araddhaviriyo viharati thamava dalhaparakkamo anikkhittadhuro kusalesu dhammesu; ","an5.110:1.6":"catunnam jhananam abhicetasikanam ditthadhammasukhaviharanam nikamalabhi hoti akicchalabhi akasiralabhi; ","an5.110:1.7":"asavanam khaya anasavam cetovimuttim pannavimuttim dittheva dhamme sayam abhinna sacchikatva upasampajja viharati. ","an5.110:1.8":"Imehi kho, bhikkhave, pancahi dhammehi samannagato bhikkhu alam arannavanapatthani pantani senasanani patisevitun”ti. ","an5.110:1.9":"Dasamam. ","an5.110:1.10":"Phasuviharavaggo pathamo. ","an5.110:2.0":"Tassuddanam ","an5.110:2.1":"Sarajjam sankito coro, ","an5.110:2.2":"Sukhumalam phasu pancamam; ","an5.110:2.3":"Ananda silasekha ca, ","an5.110:2.4":"Catuddiso arannena cati. "}