{"dhp179:0.1":"Khuddakanikaya ","dhp179:0.2":"Dhammapada ","dhp179:0.3":"Buddhavagga ","dhp179:0.4":"Maradhitaravatthu ","dhp179:1":"Yassa jitam navajiyati, ","dhp179:2":"Jitam yassa noyati koci loke; ","dhp179:3":"Tam buddhamanantagocaram, ","dhp179:4":"Apadam kena padena nessatha. ","dhp180:1":"Yassa jalini visattika, ","dhp180:2":"Tanha natthi kuhinci netave; ","dhp180:3":"Tam buddhamanantagocaram, ","dhp180:4":"Apadam kena padena nessatha. ","dhp181:0":"Devorohanavatthu ","dhp181:1":"Ye jhanapasuta dhira, ","dhp181:2":"nekkhammupasame rata; ","dhp181:3":"Devapi tesam pihayanti, ","dhp181:4":"sambuddhanam satimatam. ","dhp182:0":"Erakapattanagarajavatthu ","dhp182:1":"Kiccho manussapatilabho, ","dhp182:2":"kiccham maccana jivitam; ","dhp182:3":"Kiccham saddhammassavanam, ","dhp182:4":"kiccho buddhanamuppado. ","dhp183:0":"Anandattherapanhavatthu ","dhp183:1":"Sabbapapassa akaranam, ","dhp183:2":"kusalassa upasampada; ","dhp183:3":"Sacittapariyodapanam, ","dhp183:4":"etam buddhana sasanam. ","dhp184:1":"Khanti paramam tapo titikkha, ","dhp184:2":"Nibbanam paramam vadanti buddha; ","dhp184:3":"Na hi pabbajito parupaghati, ","dhp184:4":"Na samano hoti param vihethayanto. ","dhp185:1":"Anupavado anupaghato, ","dhp185:2":"Patimokkhe ca samvaro; ","dhp185:3":"Mattannuta ca bhattasmim, ","dhp185:4":"Pantanca sayanasanam; ","dhp185:5":"Adhicitte ca ayogo, ","dhp185:6":"Etam buddhana sasanam. ","dhp186:0":"Anabhiratabhikkhuvatthu ","dhp186:1":"Na kahapanavassena, ","dhp186:2":"titti kamesu vijjati; ","dhp186:3":"Appassada dukha kama, ","dhp186:4":"iti vinnaya pandito. ","dhp187:1":"Api dibbesu kamesu, ","dhp187:2":"ratim so nadhigacchati; ","dhp187:3":"Tanhakkhayarato hoti, ","dhp187:4":"sammasambuddhasavako. ","dhp188:0":"Aggidattabrahmanavatthu ","dhp188:1":"Bahum ve saranam yanti, ","dhp188:2":"pabbatani vanani ca; ","dhp188:3":"Aramarukkhacetyani, ","dhp188:4":"manussa bhayatajjita. ","dhp189:1":"Netam kho saranam khemam, ","dhp189:2":"netam saranamuttamam; ","dhp189:3":"Netam saranamagamma, ","dhp189:4":"sabbadukkha pamuccati. ","dhp190:1":"Yo ca buddhanca dhammanca, ","dhp190:2":"sanghanca saranam gato; ","dhp190:3":"Cattari ariyasaccani, ","dhp190:4":"sammappannaya passati. ","dhp191:1":"Dukkham dukkhasamuppadam, ","dhp191:2":"dukkhassa ca atikkamam; ","dhp191:3":"Ariyam catthangikam maggam, ","dhp191:4":"dukkhupasamagaminam. ","dhp192:1":"Etam kho saranam khemam, ","dhp192:2":"etam saranamuttamam; ","dhp192:3":"Etam saranamagamma, ","dhp192:4":"sabbadukkha pamuccati. ","dhp193:0":"Anandattherapanhavatthu ","dhp193:1":"Dullabho purisajanno, ","dhp193:2":"na so sabbattha jayati; ","dhp193:3":"Yattha so jayati dhiro, ","dhp193:4":"tam kulam sukhamedhati. ","dhp194:0":"Sambahulabhikkhuvatthu ","dhp194:1":"Sukho buddhanamuppado, ","dhp194:2":"sukha saddhammadesana; ","dhp194:3":"Sukha sanghassa samaggi, ","dhp194:4":"samagganam tapo sukho. ","dhp195:0":"Kassapadasabalassasuvannacetiyavatthu ","dhp195:1":"Pujarahe pujayato, ","dhp195:2":"buddhe yadi va savake; ","dhp195:3":"Papancasamatikkante, ","dhp195:4":"tinnasokapariddave. ","dhp196:1":"Te tadise pujayato, ","dhp196:2":"nibbute akutobhaye; ","dhp196:3":"Na sakka punnam sankhatum, ","dhp196:4":"imettamapi kenaci. ","dhp196:5":"Buddhavaggo cuddasamo. ","dhp196:6":"Pathamabhanavaram. "}