{"dhp116:0.1":"Khuddakanikaya ","dhp116:0.2":"Dhammapada ","dhp116:0.3":"Papavagga ","dhp116:0.4":"Culekasatakabrahmanavatthu ","dhp116:1":"Abhittharetha kalyane, ","dhp116:2":"papa cittam nivaraye; ","dhp116:3":"Dandhanhi karoto punnam, ","dhp116:4":"papasmim ramati mano. ","dhp117:0":"Seyyasakattheravatthu ","dhp117:1":"Papance puriso kayira, ","dhp117:2":"Na nam kayira punappunam; ","dhp117:3":"Na tamhi chandam kayiratha, ","dhp117:4":"Dukkho papassa uccayo. ","dhp118:0":"Lajadevadhitavatthu ","dhp118:1":"Punnance puriso kayira, ","dhp118:2":"kayira nam punappunam; ","dhp118:3":"Tamhi chandam kayiratha, ","dhp118:4":"sukho punnassa uccayo. ","dhp119:0":"Anathapindikasetthivatthu ","dhp119:1":"Papopi passati bhadram, ","dhp119:2":"Yava papam na paccati; ","dhp119:3":"Yada ca paccati papam, ","dhp119:4":"Atha papo papani passati. ","dhp120:1":"Bhadropi passati papam, ","dhp120:2":"Yava bhadram na paccati; ","dhp120:3":"Yada ca paccati bhadram, ","dhp120:4":"Atha bhadro bhadrani passati. ","dhp121:0":"Asannataparikkharavatthu ","dhp121:1":"Mavamannetha papassa, ","dhp121:2":"na mantam agamissati; ","dhp121:3":"Udabindunipatena, ","dhp121:4":"udakumbhopi purati; ","dhp121:5":"Balo purati papassa, ","dhp121:6":"thokam thokampi acinam. ","dhp122:0":"Bilalapadakasetthivatthu ","dhp122:1":"Mavamannetha punnassa, ","dhp122:2":"na mandam agamissati; ","dhp122:3":"Udabindunipatena, ","dhp122:4":"udakumbhopi purati; ","dhp122:5":"Dhiro purati punnassa, ","dhp122:6":"thokam thokampi acinam. ","dhp123:0":"Mahadhanavanijavatthu ","dhp123:1":"Vanijova bhayam maggam, ","dhp123:2":"appasattho mahaddhano; ","dhp123:3":"Visam jivitukamova, ","dhp123:4":"papani parivajjaye. ","dhp124:0":"Kukkutamittanesadavatthu ","dhp124:1":"Panimhi ce vano nassa, ","dhp124:2":"hareyya panina visam; ","dhp124:3":"Nabbanam visamanveti, ","dhp124:4":"natthi papam akubbato. ","dhp125:0":"Kokasunakhaluddakavatthu ","dhp125:1":"Yo appadutthassa narassa dussati, ","dhp125:2":"Suddhassa posassa ananganassa; ","dhp125:3":"Tameva balam pacceti papam, ","dhp125:4":"Sukhumo rajo pativatamva khitto. ","dhp126:0":"Manikarakulupakatissattheravatthu ","dhp126:1":"Gabbhameke uppajjanti, ","dhp126:2":"nirayam papakammino; ","dhp126:3":"Saggam sugatino yanti, ","dhp126:4":"parinibbanti anasava. ","dhp127:0":"Tayojanavatthu ","dhp127:1":"Na antalikkhe na samuddamajjhe, ","dhp127:2":"Na pabbatanam vivaram pavissa; ","dhp127:3":"Na vijjati so jagatippadeso, ","dhp127:4":"Yatthatthito mucceyya papakamma. ","dhp128:0":"Suppabuddhasakyavatthu ","dhp128:1":"Na antalikkhe na samuddamajjhe, ","dhp128:2":"Na pabbatanam vivaram pavissa; ","dhp128:3":"Na vijjati so jagatippadeso, ","dhp128:4":"Yatthatthitam nappasaheyya maccu. ","dhp128:5":"Papavaggo navamo. "}