{"dhp90:0.1":"Khuddakanikaya ","dhp90:0.2":"Dhammapada ","dhp90:0.3":"Arahantavagga ","dhp90:0.4":"Jivakapanhavatthu ","dhp90:1":"Gataddhino visokassa, ","dhp90:2":"vippamuttassa sabbadhi; ","dhp90:3":"Sabbaganthappahinassa, ","dhp90:4":"parilaho na vijjati. ","dhp91:0":"Mahakassapattheravatthu ","dhp91:1":"Uyyunjanti satimanto, ","dhp91:2":"na nikete ramanti te; ","dhp91:3":"Hamsava pallalam hitva, ","dhp91:4":"okamokam jahanti te. ","dhp92:0":"Belatthasisattheravatthu ","dhp92:1":"Yesam sannicayo natthi, ","dhp92:2":"ye parinnatabhojana; ","dhp92:3":"Sunnato animitto ca, ","dhp92:4":"vimokkho yesam gocaro; ","dhp92:5":"Akaseva sakuntanam, ","dhp92:6":"gati tesam durannaya. ","dhp93:0":"Anuruddhattheravatthu ","dhp93:1":"Yassasava parikkhina, ","dhp93:2":"ahare ca anissito; ","dhp93:3":"Sunnato animitto ca, ","dhp93:4":"vimokkho yassa gocaro; ","dhp93:5":"Akaseva sakuntanam, ","dhp93:6":"padam tassa durannayam. ","dhp94:0":"Mahakaccayanattheravatthu ","dhp94:1":"Yassindriyani samathangatani, ","dhp94:2":"Assa yatha sarathina sudanta; ","dhp94:3":"Pahinamanassa anasavassa, ","dhp94:4":"Devapi tassa pihayanti tadino. ","dhp95:0":"Sariputtattheravatthu ","dhp95:1":"Pathavisamo no virujjhati, ","dhp95:2":"Indakhilupamo tadi subbato; ","dhp95:3":"Rahadova apetakaddamo, ","dhp95:4":"Samsara na bhavanti tadino. ","dhp96:0":"Kosambivasitissattherasamaneravatthu ","dhp96:1":"Santam tassa manam hoti, ","dhp96:2":"santa vaca ca kamma ca; ","dhp96:3":"Sammadannavimuttassa, ","dhp96:4":"upasantassa tadino. ","dhp97:0":"Sariputtattheravatthu ","dhp97:1":"Assaddho akatannu ca, ","dhp97:2":"sandhicchedo ca yo naro; ","dhp97:3":"Hatavakaso vantaso, ","dhp97:4":"sa ve uttamaporiso. ","dhp98:0":"Khadiravaniyarevatattheravatthu ","dhp98:1":"Game va yadi varanne, ","dhp98:2":"Ninne va yadi va thale; ","dhp98:3":"Yattha arahanto viharanti, ","dhp98:4":"Tam bhumiramaneyyakam. ","dhp99:0":"Annataraitthivatthu ","dhp99:1":"Ramaniyani arannani, ","dhp99:2":"yattha na ramati jano; ","dhp99:3":"Vitaraga ramissanti, ","dhp99:4":"na te kamagavesino. ","dhp99:5":"Arahantavaggo sattamo. "}