{"iti63:0.1":"Itivuttaka 63 ","iti63:0.2":"Tikanipata ","iti63:0.3":"Dutiyavagga ","iti63:0.4":"Addhasutta ","iti63:1.1":"Vuttanhetam bhagavata vuttamarahatati me sutam: ","iti63:2.1":"“Tayome, bhikkhave, addha. ","iti63:2.2":"Katame tayo? ","iti63:2.3":"Atito addha, anagato addha, paccuppanno addha—","iti63:2.4":"ime kho, bhikkhave, tayo addha”ti. ","iti63:2.5":"Etamattham bhagava avoca. ","iti63:2.6":"Tatthetam iti vuccati: ","iti63:3.1":"“Akkheyyasannino satta, ","iti63:3.2":"akkheyyasmim patitthita; ","iti63:3.3":"Akkheyyam aparinnaya, ","iti63:3.4":"yogamayanti maccuno. ","iti63:4.1":"Akkheyyanca parinnaya, ","iti63:4.2":"akkhataram na mannati; ","iti63:4.3":"Phuttho vimokkho manasa, ","iti63:4.4":"santipadamanuttaram. ","iti63:5.1":"Sa ve akkheyyasampanno, ","iti63:5.2":"santo santipade rato; ","iti63:5.3":"Sankhaya sevi dhammattho, ","iti63:5.4":"sankhyam nopeti vedagu”ti. ","iti63:6.1":"Ayampi attho vutto bhagavata, iti me sutanti. ","iti63:6.2":"Catuttham. "}