{"ja365:0.1":"Jataka ","ja365:0.2":"Pancakanipata ","ja365:0.3":"Vannarohavagga ","ja365:0.4":"5. Ahitundikajataka ","ja365:1.1":"“Dhuttomhi samma sumukha, ","ja365:1.2":"jute akkhaparajito; ","ja365:1.3":"Harehi ambapakkani, ","ja365:1.4":"viriyam te bhakkhayamase”. ","ja365:2.1":"“Alikam vata mam samma, ","ja365:2.2":"abhutena pasamsasi; ","ja365:2.3":"Ko te suto va dittho va, ","ja365:2.4":"sumukho nama makkato. ","ja365:3.1":"Ajjapi me tam manasi, ","ja365:3.2":"yam mam tvam ahitundika; ","ja365:3.3":"Dhannapanam pavisitva, ","ja365:3.4":"matto chatam hanasi mam. ","ja365:4.1":"Taham saram dukkhaseyyam, ","ja365:4.2":"api rajjampi karaye; ","ja365:4.3":"Nevaham yacito dajjam, ","ja365:4.4":"tatha hi bhayatajjito. ","ja365:5.1":"Yanca janna kule jatam, ","ja365:5.2":"Gabbhe tittam amaccharim; ","ja365:5.3":"Tena sakhinca mittanca, ","ja365:5.4":"Dhiro sandhatumarahati”ti. ","ja365:6.1":"Ahitundikajatakam pancamam. "}