{"ja517:0.1":"Jataka ","ja517:0.2":"Timsanipata ","ja517:0.3":"Kimchandavagga ","ja517:0.4":"7. Dakarakkhasajataka ","ja517:1.1":"“Sace vo vuyhamananam, ","ja517:1.2":"sattannam udakannave; ","ja517:1.3":"Manussabalimesano, ","ja517:1.4":"navam ganheyya rakkhaso; ","ja517:1.5":"Anupubbam katham datva, ","ja517:1.6":"muncesi dakarakkhasa”. ","ja517:2.1":"“Mataram pathamam dajjam, ","ja517:2.2":"Bhariyam datvana bhataram; ","ja517:2.3":"Tato sahayam datvana, ","ja517:2.4":"Pancamam dajjam brahmanam; ","ja517:2.5":"Chatthaham dajjamattanam, ","ja517:2.6":"Neva dajjam mahosadham”. ","ja517:3.1":"“Poseta te janetti ca, ","ja517:3.2":"digharattanukampika; ","ja517:3.3":"Chabbhi tayi padussati, ","ja517:3.4":"pandita atthadassini; ","ja517:3.5":"Annam upanisam katva, ","ja517:3.6":"vadha tam parimocayi. ","ja517:4.1":"Tam tadisim panadadim, ","ja517:4.2":"orasam gabbhadharinim; ","ja517:4.3":"Mataram kena dosena, ","ja517:4.4":"dajjasi dakarakkhino”. ","ja517:5.1":"“Dahara viyalankaram, ","ja517:5.2":"dhareti apilandhanam; ","ja517:5.3":"Dovarike anikatthe, ","ja517:5.4":"ativelam pajagghati. ","ja517:6.1":"Athopi patirajunam, ","ja517:6.2":"sayam dutani sasati; ","ja517:6.3":"Mataram tena dosena, ","ja517:6.4":"dajjaham dakarakkhino”. ","ja517:7.1":"“Itthigumbassa pavara, ","ja517:7.2":"accantam piyabhanini; ","ja517:7.3":"Anuggata silavati, ","ja517:7.4":"chayava anapayini. ","ja517:8.1":"Akkodhana punnavati, ","ja517:8.2":"pandita atthadassini; ","ja517:8.3":"Ubbarim kena dosena, ","ja517:8.4":"dajjasi dakarakkhino”. ","ja517:9.1":"“Khiddaratisamapannam, ","ja517:9.2":"anatthavasamagatam; ","ja517:9.3":"Sa mam sakana puttanam, ","ja517:9.4":"ayacam yacate dhanam. ","ja517:10.1":"Soham dadami saratto, ","ja517:10.2":"bahum uccavacam dhanam; ","ja517:10.3":"Suduccajam cajitvana, ","ja517:10.4":"paccha socami dummano; ","ja517:10.5":"Ubbarim tena dosena, ","ja517:10.6":"dajjaham dakarakkhino”. ","ja517:11.1":"“Yenocita janapada, ","ja517:11.2":"anita ca patiggaham; ","ja517:11.3":"Abhatam pararajjebhi, ","ja517:11.4":"abhitthaya bahum dhanam. ","ja517:12.1":"Dhanuggahanam pavaram, ","ja517:12.2":"suram tikhinamantinam; ","ja517:12.3":"Bhataram kena dosena, ","ja517:12.4":"dajjasi dakarakkhino”. ","ja517:13.1":"“Yenocita janapada, ","ja517:13.2":"anita ca patiggaham; ","ja517:13.3":"Abhatam pararajjebhi, ","ja517:13.4":"abhitthaya bahum dhanam. ","ja517:14.1":"Dhanuggahanam pavaro, ","ja517:14.2":"suro tikhinamanti ca; ","ja517:14.3":"Mayayam sukhito raja, ","ja517:14.4":"atimannati darako. ","ja517:15.1":"Upatthanampi me ayye, ","ja517:15.2":"na so eti yatha pure; ","ja517:15.3":"Bhataram tena dosena, ","ja517:15.4":"dajjaham dakarakkhino”. ","ja517:16.1":"“Ekarattena ubhayo, ","ja517:16.2":"tvanceva dhanusekha ca; ","ja517:16.3":"Ubho jatettha pancala, ","ja517:16.4":"sahaya susamavaya. ","ja517:17.1":"Cariya tam anubandhittho, ","ja517:17.2":"ekadukkhasukho tava; ","ja517:17.3":"Ussukko te divarattim, ","ja517:17.4":"sabbakiccesu byavato; ","ja517:17.5":"Sahayam kena dosena, ","ja517:17.6":"dajjasi dakarakkhino”. ","ja517:18.1":"“Cariya mam ayam ayye, ","ja517:18.2":"pajagghittho maya saha; ","ja517:18.3":"Ajjapi tena vannena, ","ja517:18.4":"ativelam pajagghati. ","ja517:19.1":"Ubbariyapiham ayye, ","ja517:19.2":"mantayami rahogato; ","ja517:19.3":"Anamanto pavisati, ","ja517:19.4":"pubbe appativedito. ","ja517:20.1":"Laddhadvaro katokaso, ","ja517:20.2":"ahirikam anadaram; ","ja517:20.3":"Sahayam tena dosena, ","ja517:20.4":"dajjaham dakarakkhino”. ","ja517:21.1":"“Kusalo sabbanimittanam, ","ja517:21.2":"rutannu agatagamo; ","ja517:21.3":"Uppate supine yutto, ","ja517:21.4":"niyyane ca pavesane. ","ja517:22.1":"Pattho bhumantalikkhasmim, ","ja517:22.2":"Nakkhattapadakovido; ","ja517:22.3":"Brahmanam kena dosena, ","ja517:22.4":"Dajjasi dakarakkhino”. ","ja517:23.1":"“Parisayampi me ayye, ","ja517:23.2":"ummilitva udikkhati; ","ja517:23.3":"Tasma accabhamum luddam, ","ja517:23.4":"dajjaham dakarakkhino”. ","ja517:24.1":"“Sasamuddapariyayam, ","ja517:24.2":"mahim sagarakundalam; ","ja517:24.3":"Vasundharam avasasi, ","ja517:24.4":"amaccaparivarito. ","ja517:25.1":"Caturanto maharattho, ","ja517:25.2":"vijitavi mahabbalo; ","ja517:25.3":"Pathabya ekarajasi, ","ja517:25.4":"yaso te vipulam gato. ","ja517:26.1":"Solasitthisahassani, ","ja517:26.2":"amuttamanikundala; ","ja517:26.3":"Nanajanapada nari, ","ja517:26.4":"devakannupama subha. ","ja517:27.1":"Evam sabbangasampannam, ","ja517:27.2":"sabbakamasamiddhinam; ","ja517:27.3":"Sukhitanam piyam digham, ","ja517:27.4":"jivitam ahu khattiya. ","ja517:28.1":"Atha tvam kena vannena, ","ja517:28.2":"kena va pana hetuna; ","ja517:28.3":"Panditam anurakkhanto, ","ja517:28.4":"panam cajasi duccajam”. ","ja517:29.1":"“Yatopi agato ayye, ","ja517:29.2":"mama hattham mahosadho; ","ja517:29.3":"Nabhijanami dhirassa, ","ja517:29.4":"anumattampi dukkatam. ","ja517:30.1":"Sace ca kismici kale, ","ja517:30.2":"maranam me pure siya; ","ja517:30.3":"So me putte paputte ca, ","ja517:30.4":"sukhapeyya mahosadho. ","ja517:31.1":"Anagatam paccuppannam, ","ja517:31.2":"sabbamatthampi passati; ","ja517:31.3":"Anaparadhakammantam, ","ja517:31.4":"na dajjam dakarakkhino”. ","ja517:32.1":"“Idam sunatha pancala, ","ja517:32.2":"culaneyyassa bhasitam; ","ja517:32.3":"Panditam anurakkhanto, ","ja517:32.4":"panam cajati duccajam. ","ja517:33.1":"Matu bhariyaya bhatucca, ","ja517:33.2":"sakhino brahmanassa ca; ","ja517:33.3":"Attano capi pancalo, ","ja517:33.4":"channam cajati jivitam. ","ja517:34.1":"Evam mahatthika panna, ","ja517:34.2":"nipuna sadhucintini; ","ja517:34.3":"Ditthadhammahitatthaya, ","ja517:34.4":"samparayasukhaya ca”ti. ","ja517:35.1":"Dakarakkhasajatakam sattamam. "}