{"pv44:0.1":"Petavatthu ","pv44:0.2":"Mahavagga ","pv44:0.3":"9. Guthakhadakapetivatthu ","pv44:1.1":"“Guthakupato uggantva, ","pv44:1.2":"ka nu dina patitthasi; ","pv44:1.3":"Nissamsayam papakammanta, ","pv44:1.4":"kim nu saddahase tuvan”ti. ","pv44:2.1":"“Aham bhadante petimhi, ","pv44:2.2":"duggata yamalokika; ","pv44:2.3":"Papakammam karitvana, ","pv44:2.4":"petalokam ito gata”ti. ","pv44:3.1":"“Kim nu kayena vacaya, ","pv44:3.2":"manasa dukkatam katam; ","pv44:3.3":"Kissa kammavipakena, ","pv44:3.4":"idam dukkham nigacchasi”ti. ","pv44:4.1":"“Ahu avasiko mayham, ","pv44:4.2":"issuki kulamacchari; ","pv44:4.3":"Ajjhasito mayham ghare, ","pv44:4.4":"kadariyo paribhasako. ","pv44:5.1":"Tassaham vacanam sutva, ","pv44:5.2":"bhikkhavo paribhasisam; ","pv44:5.3":"Tassa kammavipakena, ","pv44:5.4":"petalokam ito gata”ti. ","pv44:6.1":"“Amitto mittavannena, ","pv44:6.2":"yo te asi kulupako; ","pv44:6.3":"Kayassa bheda duppanno, ","pv44:6.4":"kim nu pecca gatim gato”ti. ","pv44:7.1":"“Tassevaham papakammassa, ","pv44:7.2":"sise titthami matthake; ","pv44:7.3":"So ca paravisayam patto, ","pv44:7.4":"mameva paricarako. ","pv44:8.1":"Yam bhadante hadantanne, ","pv44:8.2":"etam me hoti bhojanam; ","pv44:8.3":"Ahanca kho yam hadami, ","pv44:8.4":"etam so upajivati”ti. ","pv44:9.1":"Guthakhadakapetivatthu navamam. "}