{"sn1.58:0.1":"Samyutta Nikaya 1.58 ","sn1.58:0.2":"6. Jaravagga ","sn1.58:0.3":"Uppathasutta ","sn1.58:1.1":"“Kimsu uppatho akkhato, ","sn1.58:1.2":"kimsu rattindivakkhayo; ","sn1.58:1.3":"Kim malam brahmacariyassa, ","sn1.58:1.4":"kim sinanamanodakan”ti. ","sn1.58:2.1":"“Rago uppatho akkhato, ","sn1.58:2.2":"Vayo rattindivakkhayo; ","sn1.58:2.3":"Itthi malam brahmacariyassa, ","sn1.58:2.4":"Etthayam sajjate paja; ","sn1.58:2.5":"Tapo ca brahmacariyanca, ","sn1.58:2.6":"Tam sinanamanodakan”ti. "}