{"sn18.8:0.1":"Samyutta Nikaya 18.8 ","sn18.8:0.2":"1. Pathamavagga ","sn18.8:0.3":"Tanhasutta ","sn18.8:1.1":"Savatthiyam viharati. ","sn18.8:1.2":"“Tam kim mannasi, rahula, ","sn18.8:1.3":"rupatanha nicca va anicca va”ti? ","sn18.8:1.4":"“Anicca, bhante” … ","sn18.8:1.5":"“saddatanha …pe… ","sn18.8:1.6":"gandhatanha … ","sn18.8:1.7":"rasatanha … ","sn18.8:1.8":"photthabbatanha … ","sn18.8:1.9":"dhammatanha nicca va anicca va”ti? ","sn18.8:1.10":"“Anicca, bhante” … ","sn18.8:1.11":"“evam passam, rahula, sutava ariyasavako rupatanhayapi nibbindati …pe… saddatanhayapi nibbindati … gandhatanhayapi nibbindati … rasatanhayapi nibbindati … photthabbatanhayapi nibbindati … dhammatanhayapi nibbindati …pe… ","sn18.8:1.12":"pajanati”ti. ","sn18.8:1.13":"Atthamam. "}