{"sn22.33:0.1":"Samyutta Nikaya 22.33 ","sn22.33:0.2":"4. Natumhakavagga ","sn22.33:0.3":"Natumhakasutta ","sn22.33:1.1":"Savatthinidanam. ","sn22.33:1.2":"“Yam, bhikkhave, na tumhakam, tam pajahatha. ","sn22.33:1.3":"Tam vo pahinam hitaya sukhaya bhavissati. ","sn22.33:1.4":"Kinca, bhikkhave, na tumhakam? ","sn22.33:1.5":"Rupam, bhikkhave, na tumhakam, tam pajahatha. ","sn22.33:1.6":"Tam vo pahinam hitaya sukhaya bhavissati. ","sn22.33:1.7":"Vedana na tumhakam, tam pajahatha. ","sn22.33:1.8":"Sa vo pahina hitaya sukhaya bhavissati. ","sn22.33:1.9":"Sanna na tumhakam … ","sn22.33:1.10":"sankhara na tumhakam, te pajahatha. ","sn22.33:1.11":"Te vo pahina hitaya sukhaya bhavissanti. ","sn22.33:1.12":"Vinnanam na tumhakam, tam pajahatha. ","sn22.33:1.13":"Tam vo pahinam hitaya sukhaya bhavissati. ","sn22.33:2.1":"Seyyathapi, bhikkhave, yam imasmim jetavane tinakatthasakhapalasam tam jano hareyya va daheyya va yathapaccayam va kareyya. ","sn22.33:2.2":"Api nu tumhakam evamassa: ","sn22.33:2.3":"‘amhe jano harati va dahati va yathapaccayam va karoti’”ti? ","sn22.33:2.4":"“No hetam, bhante”. ","sn22.33:2.5":"“Tam kissa hetu”? ","sn22.33:2.6":"“Na hi no etam, bhante, atta va attaniyam va”ti. ","sn22.33:2.7":"“Evameva kho, bhikkhave, rupam na tumhakam, tam pajahatha. ","sn22.33:2.8":"Tam vo pahinam hitaya sukhaya bhavissati. ","sn22.33:2.9":"Vedana na tumhakam, tam pajahatha. ","sn22.33:2.10":"Sa vo pahina hitaya sukhaya bhavissati. ","sn22.33:2.11":"Sanna na tumhakam … ","sn22.33:2.12":"sankhara na tumhakam … ","sn22.33:2.13":"vinnanam na tumhakam, tam pajahatha. ","sn22.33:2.14":"Tam vo pahinam hitaya sukhaya bhavissati”ti. ","sn22.33:2.15":"Pathamam. "}