{"sn22.46:0.1":"Samyutta Nikaya 22.46 ","sn22.46:0.2":"5. Attadipavagga ","sn22.46:0.3":"Dutiyaaniccasutta ","sn22.46:1.1":"Savatthinidanam. ","sn22.46:1.2":"“Rupam, bhikkhave, aniccam. ","sn22.46:1.3":"Yadaniccam tam dukkham; ","sn22.46:1.4":"yam dukkham tadanatta; ","sn22.46:1.5":"yadanatta tam ‘netam mama, nesohamasmi, na meso atta’ti evametam yathabhutam sammappannaya datthabbam. ","sn22.46:1.6":"Vedana anicca … ","sn22.46:1.7":"sanna anicca … ","sn22.46:1.8":"sankhara anicca … ","sn22.46:1.9":"vinnanam aniccam. ","sn22.46:1.10":"Yadaniccam tam dukkham; ","sn22.46:1.11":"yam dukkham tadanatta; ","sn22.46:1.12":"yadanatta tam ‘netam mama, nesohamasmi, na meso atta’ti evametam yathabhutam sammappannaya datthabbam. ","sn22.46:2.1":"Evametam yathabhutam sammappannaya passato pubbantanuditthiyo na honti. ","sn22.46:2.2":"Pubbantanuditthinam asati, aparantanuditthiyo na honti. ","sn22.46:2.3":"Aparantanuditthinam asati, thamaso paramaso na hoti. ","sn22.46:2.4":"Thamase paramase asati rupasmim … ","sn22.46:2.5":"vedanaya … ","sn22.46:2.6":"sannaya … ","sn22.46:2.7":"sankharesu … ","sn22.46:2.8":"vinnanasmim cittam virajjati vimuccati anupadaya asavehi. ","sn22.46:2.9":"Vimuttatta thitam. Thitatta santusitam. Santusitatta na paritassati. Aparitassam paccattanneva parinibbayati. ","sn22.46:2.10":"‘Khina jati, vusitam brahmacariyam, katam karaniyam, naparam itthattaya’ti pajanati”ti. ","sn22.46:2.11":"Catuttham. "}