{"sn23.4:0.1":"Samyutta Nikaya 23.4 ","sn23.4:0.2":"1. Pathamamaravagga ","sn23.4:0.3":"Parinneyyasutta ","sn23.4:1.1":"Savatthinidanam. ","sn23.4:1.2":"Ayasma radho yena bhagava tenupasankami; upasankamitva bhagavantam abhivadetva ekamantam nisidi. Ekamantam nisinnam kho ayasmantam radham bhagava etadavoca: ","sn23.4:2.1":"“Parinneyye ca, radha, dhamme desessami parinnanca parinnatavim puggalanca. ","sn23.4:2.2":"Tam sunahi, sadhukam manasi karohi; bhasissami”ti. ","sn23.4:2.3":"“Evam, bhante”ti kho ayasma radho bhagavato paccassosi. ","sn23.4:2.4":"Bhagava etadavoca: ","sn23.4:2.5":"“katame ca, radha, parinneyya dhamma? ","sn23.4:2.6":"Rupam kho, radha, parinneyyo dhammo, vedana parinneyyo dhammo, sanna parinneyyo dhammo, sankhara parinneyyo dhammo, vinnanam parinneyyo dhammo. ","sn23.4:2.7":"Ime vuccanti, radha, parinneyya dhamma. ","sn23.4:2.8":"Katama ca, radha, parinna? ","sn23.4:2.9":"Yo kho, radha, ragakkhayo dosakkhayo mohakkhayo—","sn23.4:2.10":"ayam vuccati, radha, parinna. ","sn23.4:2.11":"Katamo ca, radha, parinnatavi puggalo? ","sn23.4:2.12":"‘Araha’tissa vacaniyam. ","sn23.4:2.13":"Yvayam ayasma evamnamo evangotto—","sn23.4:2.14":"ayam vuccati, radha, parinnatavi puggalo”ti. ","sn23.4:2.15":"Catuttham. "}