{"sn33.55:0.1":"Samyutta Nikaya 33.55 ","sn33.55:0.2":"1. Vacchagottavagga ","sn33.55:0.3":"Vinnanaappaccakkhakammasutta ","sn33.55:1.1":"Savatthinidanam. ","sn33.55:1.2":"“Vinnane kho, vaccha, appaccakkhakamma, vinnanasamudaye appaccakkhakamma, vinnananirodhe appaccakkhakamma, vinnananirodhagaminiya patipadaya appaccakkhakamma; ","sn33.55:1.3":"evamimani anekavihitani ditthigatani loke uppajjanti—","sn33.55:1.4":"sassato lokoti va, asassato lokoti va …pe… ","sn33.55:1.5":"neva hoti na na hoti tathagato param maranati vati. ","sn33.55:1.6":"Ayam kho, vaccha, hetu, ayam paccayo, yanimani anekavihitani ditthigatani loke uppajjanti—","sn33.55:1.7":"sassato lokoti va, asassato lokoti va, antava lokoti va, anantava lokoti va, tam jivam tam sariranti va, annam jivam annam sariranti va, hoti tathagato param maranati va, na hoti tathagato param maranati va, hoti ca na ca hoti tathagato param maranati va, neva hoti na na hoti tathagato param maranati va”ti. ","sn33.55:1.8":"Pancapannasamam. ","sn33.55:1.9":"Vacchagottavaggo pathamo. ","sn33.55:2.0":"Tassuddanam ","sn33.55:2.1":"Annana adassana ceva, ","sn33.55:2.2":"Anabhisamaya ananubodha; ","sn33.55:2.3":"Appativedha asallakkhana, ","sn33.55:2.4":"Anupalakkhanena appaccupalakkhana; ","sn33.55:2.5":"Asamapekkhana appaccupekkhana, ","sn33.55:2.6":"Appaccakkhakammanti. ","sn33.55:2.7":"Vacchagottasamyuttam samattam. "}