{"sn35.128:0.1":"Samyutta Nikaya 35.128 ","sn35.128:0.2":"13. Gahapativagga ","sn35.128:0.3":"Sonasutta ","sn35.128:1.1":"Ekam samayam bhagava rajagahe viharati veluvane kalandakanivape. ","sn35.128:1.2":"Atha kho sono gahapatiputto yena bhagava tenupasankami; upasankamitva bhagavantam abhivadetva ekamantam nisidi. Ekamantam nisinno kho sono gahapatiputto bhagavantam etadavoca: ","sn35.128:1.3":"“ko nu kho, bhante, hetu, ko paccayo yena m’idhekacce satta dittheva dhamme no parinibbayanti? ","sn35.128:1.4":"Ko pana, bhante, hetu, ko paccayo yena m’idhekacce satta dittheva dhamme parinibbayanti”ti? ","sn35.128:1.5":"(Yatha purimasuttantam, evam vittharetabbam.) ","sn35.128:1.6":"Ayam kho, sona, hetu, ayam paccayo yena m’idhekacce satta dittheva dhamme parinibbayantiti. ","sn35.128:1.7":"Pancamam. "}