{"sn48.66:0.1":"Samyutta Nikaya 48.66 ","sn48.66:0.2":"7. Bodhipakkhiyavagga ","sn48.66:0.3":"Dutiyaphalasutta ","sn48.66:1.1":"“Pancimani, bhikkhave, indriyani. ","sn48.66:1.2":"Katamani panca? ","sn48.66:1.3":"Saddhindriyam …pe… pannindriyam—","sn48.66:1.4":"imani kho, bhikkhave, pancindriyani. ","sn48.66:1.5":"Imesam kho, bhikkhave, pancannam indriyanam bhavitatta bahulikatatta satta phala sattanisamsa patikankha. ","sn48.66:1.6":"Katame satta phala sattanisamsa? ","sn48.66:1.7":"Dittheva dhamme patikacca annam aradheti, ","sn48.66:1.8":"no ce dittheva dhamme patikacca annam aradheti, atha maranakale annam aradheti. ","sn48.66:1.9":"No ce dittheva dhamme annam aradheti, no ce maranakale annam aradheti, atha pancannam orambhagiyanam samyojananam parikkhaya antaraparinibbayi hoti, ","sn48.66:1.10":"upahaccaparinibbayi hoti, ","sn48.66:1.11":"asankharaparinibbayi hoti, ","sn48.66:1.12":"sasankharaparinibbayi hoti, ","sn48.66:1.13":"uddhamsoto hoti akanitthagami. ","sn48.66:1.14":"Imesam kho, bhikkhave, pancannam indriyanam bhavitatta bahulikatatta ime satta phala sattanisamsa patikankha”ti. ","sn48.66:1.15":"Chattham. "}