{"sn50.45-54:0.1":"Samyutta Nikaya 50.45–54 ","sn50.45-54:0.2":"5. Oghavagga ","sn50.45-54:0.3":"Oghadisutta ","sn50.45-54:1.1":"“Pancimani, bhikkhave, uddhambhagiyani samyojanani. ","sn50.45-54:1.2":"Katamani panca? ","sn50.45-54:1.3":"Ruparago, aruparago, mano, uddhaccam, avijja—","sn50.45-54:1.4":"imani kho, bhikkhave, pancuddhambhagiyani samyojanani. ","sn50.45-54:1.5":"Imesam kho, bhikkhave, pancannam uddhambhagiyanam samyojananam abhinnaya parinnaya parikkhayaya pahanaya panca balani bhavetabbani. ","sn50.45-54:1.6":"Katamani panca? ","sn50.45-54:1.7":"Idha, bhikkhave, bhikkhu, saddhabalam bhaveti vivekanissitam viraganissitam nirodhanissitam vossaggaparinamim, ","sn50.45-54:1.8":"viriyabalam …pe… ","sn50.45-54:1.9":"satibalam … ","sn50.45-54:1.10":"samadhibalam … ","sn50.45-54:1.11":"pannabalam bhaveti vivekanissitam viraganissitam nirodhanissitam vossaggaparinamim. ","sn50.45-54:1.12":"Imesam kho, bhikkhave, pancannam uddhambhagiyanam samyojananam abhinnaya parinnaya parikkhayaya pahanaya imani panca balani bhavetabbani”ti. ","sn50.45-54:1.13":"(Evam vittharetabba.) "}