{"sn7.16:0.1":"Samyutta Nikaya 7.16 ","sn7.16:0.2":"2. Upasakavagga ","sn7.16:0.3":"Paccanikasutta ","sn7.16:1.1":"Savatthinidanam. ","sn7.16:1.2":"Tena kho pana samayena paccanikasato nama brahmano savatthiyam pativasati. ","sn7.16:1.3":"Atha kho paccanikasatassa brahmanassa etadahosi: ","sn7.16:1.4":"“yannunaham yena samano gotamo tenupasankameyyam. ","sn7.16:1.5":"Yam yadeva samano gotamo bhasissati tam tadevassaham paccanikassan”ti. ","sn7.16:1.6":"Tena kho pana samayena bhagava abbhokase cankamati. ","sn7.16:1.7":"Atha kho paccanikasato brahmano yena bhagava tenupasankami; upasankamitva bhagavantam cankamantam etadavoca: ","sn7.16:1.8":"“bhana samanadhamman”ti. ","sn7.16:2.1":"“Na paccanikasatena, ","sn7.16:2.2":"suvijanam subhasitam; ","sn7.16:2.3":"Upakkilitthacittena, ","sn7.16:2.4":"sarambhabahulena ca. ","sn7.16:3.1":"Yo ca vineyya sarambham, ","sn7.16:3.2":"appasadanca cetaso; ","sn7.16:3.3":"Aghatam patinissajja, ","sn7.16:3.4":"sa ve janna subhasitan”ti. ","sn7.16:4.1":"Evam vutte, paccanikasato brahmano bhagavantam etadavoca: ","sn7.16:4.2":"“abhikkantam, bho gotama, abhikkantam, bho gotama …pe… ","sn7.16:4.3":"upasakam mam bhavam gotamo dharetu ajjatagge panupetam saranam gatan”ti. "}