{"tha-ap275:0.1":"Therapadana ","tha-ap275:0.2":"Suvannabibbohanavagga ","tha-ap275:0.3":"3 Cankotakiyattheraapadana ","tha-ap275:1.1":"“Mahasamuddam nissaya, ","tha-ap275:1.2":"vasati pabbatantare; ","tha-ap275:1.3":"Paccuggantvana katvana, ","tha-ap275:1.4":"cankotaka madasaham. ","tha-ap275:2.1":"Siddhatthassa mahesino, ","tha-ap275:2.2":"sabbasattanukampino; ","tha-ap275:2.3":"Pupphacankotakam datva, ","tha-ap275:2.4":"kappam saggamhi modaham. ","tha-ap275:3.1":"Catunnavutito kappe, ","tha-ap275:3.2":"cankotakamadam tada; ","tha-ap275:3.3":"Duggatim nabhijanami, ","tha-ap275:3.4":"cankotakassidam phalam. ","tha-ap275:4.1":"Patisambhida catasso, ","tha-ap275:4.2":"…pe… ","tha-ap275:4.3":"katam buddhassa sasanam”. ","tha-ap275:5.1":"Ittham sudam ayasma cankotakiyo thero ima gathayo abhasitthati. ","tha-ap275:6.1":"Cankotakiyattherassapadanam tatiyam. "}