{"an8.91-117:0.1":"Numbered Discourses 8 ","an8.91-117:0.2":"10. Similarity ","an8.91-117:0.3":"Untitled Discourses With Various Laywomen on the Sabbath ","an8.91-117:1.1":"And then the lay woman Bojjha … Sirima … Paduma … Sutana … Manuja … Uttara … Mutta … Khema … Soma … Ruci … Cundi … Bimbi … Sumana … Mallika … Tissa … Tissamata … Sona … Sona’s mother … Kana … Kanamata … Uttara, Nanda’s mother … Visakha Migara’s mother … the lay woman Khujjuttara … the lay woman Samavati … Suppavasa the Koliyan … the lay woman Suppiya … the housewife Nakula’s mother … ","an8.91-117:1.2":""}